[
    {
        "type": "refactor",
        "module": "modules.projet",
        "obj": "Projet",
        "line": 18,
        "column": 0,
        "endLine": 18,
        "endColumn": 12,
        "path": "modules\\projet.py",
        "symbol": "too-many-instance-attributes",
        "message": "Too many instance attributes (13/7)",
        "message-id": "R0902"
    },
    {
        "type": "refactor",
        "module": "modules.tache",
        "obj": "Tache.__init__",
        "line": 23,
        "column": 4,
        "endLine": 23,
        "endColumn": 16,
        "path": "modules\\tache.py",
        "symbol": "too-many-arguments",
        "message": "Too many arguments (7/5)",
        "message-id": "R0913"
    }
]
